pynordpool/__init__.py
pynordpool/const.py
pynordpool/exceptions.py
pynordpool/model.py
pynordpool/py.typed
pynordpool/util.py
pynordpool-0.3.1.dist-info/METADATA
pynordpool-0.3.1.dist-info/WHEEL
pynordpool-0.3.1.dist-info/licenses/LICENSE
pynordpool-0.3.1.dist-info/RECORD
