Metadata-Version: 2.4
Name: pynordpool
Version: 0.3.1
Summary: Retrieve values from API at Nord Pool.
License: MIT
License-File: LICENSE
Keywords: nordpool,Nord Pool,api,async,client
Author: G Johansson
Author-email: goran.johansson@shiftit.se
Maintainer: G Johansson
Maintainer-email: goran.johansson@shiftit.se
Requires-Python: >=3.11,<4.0
Classifier: Development Status :: 5 - Production/Stable
Classifier: Intended Audience :: Developers
Classifier: License :: OSI Approved :: MIT License
Classifier: Natural Language :: English
Classifier: Programming Language :: Python :: 3
Classifier: Programming Language :: Python :: 3.11
Classifier: Programming Language :: Python :: 3.12
Classifier: Programming Language :: Python :: 3.13
Classifier: Programming Language :: Python :: 3.14
Classifier: Topic :: Software Development :: Libraries :: Python Modules
Requires-Dist: aiohttp (>=3.9.2)
Project-URL: Bug Tracker, https://github.com/gjohansson-ST/pynordpool/issues
Project-URL: Changelog, https://github.com/gjohansson-ST/pynordpool/releases
Project-URL: Documentation, https://github.com/gjohansson-ST/pynordpool
Project-URL: Homepage, https://github.com/gjohansson-ST/pynordpool
Project-URL: Repository, https://github.com/gjohansson-ST/pynordpool
